{
  "project_info": {
    "project_number": "980120019445",
    "project_id": "fir-berandal",
    "storage_bucket": "fir-berandal.appspot.com"
  },
  "client": [
    {
      "client_info": {
        "mobilesdk_app_id": "1:980120019445:android:b1d020aada02716ee340bc",
        "android_client_info": {
          "package_name": "com.capekngoding.flutter_hyper_ui"
        }
      },
      "oauth_client": [
        {
          "client_id": "980120019445-d9s1coeci2mo0d87nehkcqhqviiuhd8d.apps.googleusercontent.com",
          "client_type": 3
        }
      ],
      "api_key": [
        {
          "current_key": "AIzaSyA5ySyAFAohJWesDG32FvB0L7JW18i7k8U"
        }
      ],
      "services": {
        "appinvite_service": {
          "other_platform_oauth_client": [
            {
              "client_id": "980120019445-d9s1coeci2mo0d87nehkcqhqviiuhd8d.apps.googleusercontent.com",
              "client_type": 3
            },
            {
              "client_id": "980120019445-ckg4pu17tf74o8iehueets3q26guqbjg.apps.googleusercontent.com",
              "client_type": 2,
              "ios_info": {
                "bundle_id": "com.example.flutterHyperUiFire"
              }
            }
          ]
        }
      }
    },
    {
      "client_info": {
        "mobilesdk_app_id": "1:980120019445:android:808d8edb8df3a6d9e340bc",
        "android_client_info": {
          "package_name": "com.codekaze.flutter_hyper_ui"
        }
      },
      "oauth_client": [
        {
          "client_id": "980120019445-d9s1coeci2mo0d87nehkcqhqviiuhd8d.apps.googleusercontent.com",
          "client_type": 3
        }
      ],
      "api_key": [
        {
          "current_key": "AIzaSyA5ySyAFAohJWesDG32FvB0L7JW18i7k8U"
        }
      ],
      "services": {
        "appinvite_service": {
          "other_platform_oauth_client": [
            {
              "client_id": "980120019445-d9s1coeci2mo0d87nehkcqhqviiuhd8d.apps.googleusercontent.com",
              "client_type": 3
            },
            {
              "client_id": "980120019445-ckg4pu17tf74o8iehueets3q26guqbjg.apps.googleusercontent.com",
              "client_type": 2,
              "ios_info": {
                "bundle_id": "com.example.flutterHyperUiFire"
              }
            }
          ]
        }
      }
    },
    {
      "client_info": {
        "mobilesdk_app_id": "1:980120019445:android:38a52f4a16f7273be340bc",
        "android_client_info": {
          "package_name": "com.codekaze.flutterx"
        }
      },
      "oauth_client": [
        {
          "client_id": "980120019445-d9s1coeci2mo0d87nehkcqhqviiuhd8d.apps.googleusercontent.com",
          "client_type": 3
        }
      ],
      "api_key": [
        {
          "current_key": "AIzaSyA5ySyAFAohJWesDG32FvB0L7JW18i7k8U"
        }
      ],
      "services": {
        "appinvite_service": {
          "other_platform_oauth_client": [
            {
              "client_id": "980120019445-d9s1coeci2mo0d87nehkcqhqviiuhd8d.apps.googleusercontent.com",
              "client_type": 3
            },
            {
              "client_id": "980120019445-ckg4pu17tf74o8iehueets3q26guqbjg.apps.googleusercontent.com",
              "client_type": 2,
              "ios_info": {
                "bundle_id": "com.example.flutterHyperUiFire"
              }
            }
          ]
        }
      }
    },
    {
      "client_info": {
        "mobilesdk_app_id": "1:980120019445:android:0cd68540f5b76fc6e340bc",
        "android_client_info": {
          "package_name": "com.capekngoding.flutter_hyper_ui_fire"
        }
      },
      "oauth_client": [
        {
          "client_id": "980120019445-d9s1coeci2mo0d87nehkcqhqviiuhd8d.apps.googleusercontent.com",
          "client_type": 3
        }
      ],
      "api_key": [
        {
          "current_key": "AIzaSyA5ySyAFAohJWesDG32FvB0L7JW18i7k8U"
        }
      ],
      "services": {
        "appinvite_service": {
          "other_platform_oauth_client": [
            {
              "client_id": "980120019445-d9s1coeci2mo0d87nehkcqhqviiuhd8d.apps.googleusercontent.com",
              "client_type": 3
            },
            {
              "client_id": "980120019445-ckg4pu17tf74o8iehueets3q26guqbjg.apps.googleusercontent.com",
              "client_type": 2,
              "ios_info": {
                "bundle_id": "com.example.flutterHyperUiFire"
              }
            }
          ]
        }
      }
    }
  ],
  "configuration_version": "1"
}